pyotpx/__init__.py
pyotpx/emailer.py
pyotpx/otp.py
pyotpx-1.0.1.dist-info/LICENSE
pyotpx-1.0.1.dist-info/METADATA
pyotpx-1.0.1.dist-info/WHEEL
pyotpx-1.0.1.dist-info/top_level.txt
pyotpx-1.0.1.dist-info/RECORD
