Metadata-Version: 2.2
Name: pyotpx
Version: 1.0.1
Summary: A free and secure OTP system with email verification
Author: NotHerXenon
Author-email: PyOTPX@gmail.com
License: MIT
Classifier: Programming Language :: Python :: 3
Classifier: License :: OSI Approved :: MIT License
Classifier: Operating System :: OS Independent
License-File: LICENSE
Dynamic: author
Dynamic: author-email
Dynamic: classifier
Dynamic: description
Dynamic: description-content-type
Dynamic: license
Dynamic: summary
